lambdatool/__init__.py
lambdatool/cf_import_things.py
lambdatool/command.py
lambdatool/lambda_creator.py
lambdatool/lambda_deployer.py
lambdatool/parts.py
lambdatool/pip_util.py
lambdatool/stack_tool.py
lambdatool/template_creator.py
lambdatool/utility.py
lambdatool/template/template_template
lambdatool/template/service/.lambdatool
lambdatool/template/service/main.py
lambdatool/template/service/requirements.txt
lambdatool/template/service/config/dev/function.properties
lambdatool/template/simple/.lambdatool
lambdatool/template/simple/main.py
lambdatool/template/simple/requirements.txt
lambdatool/template/simple/utility.py
lambdatool/template/simple/config/config.ini
lambdatool/template/simple/config/dev/function.properties
LambdaTool-0.9.10.dist-info/LICENSE
LambdaTool-0.9.10.dist-info/METADATA
LambdaTool-0.9.10.dist-info/WHEEL
LambdaTool-0.9.10.dist-info/entry_points.txt
LambdaTool-0.9.10.dist-info/top_level.txt
LambdaTool-0.9.10.dist-info/RECORD
