Metadata-Version: 2.1
Name: LambdaTool
Version: 0.9.10
Summary: Python Lambda utility
Home-page: https://github.com/muckamuck/lambda-tool
Author: Chuck Muckamuck
Author-email: Chuck.Muckamuck@gmail.com
License-File: LICENSE
Requires-Dist: boto3 (>=1.4.3)
Requires-Dist: GitPython (>=2.1.7)
Requires-Dist: Click (>=6.7)
Requires-Dist: PyYAML (>=3.12)
Requires-Dist: pymongo (>=3.4.0)
Requires-Dist: stackility (>=0.3)
Requires-Dist: Mako (>=1.0.6)
